logtator-0.2.1.dist-info/METADATA
logtator-0.2.1.dist-info/WHEEL
logtator-0.2.1.dist-info/entry_points.txt
logtator/__init__.py
logtator/_base.py
logtator/_loggers.py
logtator/_settings.py
logtator/annotations.py
logtator/encoders.py
logtator/formatters.py
logtator-0.2.1.dist-info/RECORD
