Metadata-Version: 2.1
Name: logtator
Version: 0.2.1
Summary: logging dictator which makes logging just work
Author: Martin Zaťko
License: MIT
Requires-Python: >=3.11
Provides-Extra: ddtrace
Requires-Dist: ddtrace>=2.7.0; extra == "ddtrace"
